FoxitPDFConversionSDKPython3-3.0.0.dist-info/top_level.txt
FoxitPDFConversionSDKPython3-3.0.0.dist-info/RECORD
FoxitPDFConversionSDKPython3-3.0.0.dist-info/METADATA
FoxitPDFConversionSDKPython3-3.0.0.dist-info/WHEEL
FoxitPDFConversionSDKPython3-3.0.0.dist-info/legal.txt
FoxitPDFConversionSDKPython3/_fpdfconversionsdk.so
FoxitPDFConversionSDKPython3/__init__.py
FoxitPDFConversionSDKPython3/fpdfconversionsdk.py
