Metadata-Version: 2.1
Name: FoxitPDFConversionSDKPython3
Version: 3.0.0
Summary: Foxit PDF CONVERSION SDK For Python3
Home-page: https://developers.foxit.com
Author: Foxit Software Inc.
Author-email: support@foxitsoftware.com
License: Other/Proprietary License (Commercial)
Keywords: PDF CONVERSION SDK
Platform: UNKNOWN
Classifier: Development Status :: 5 - Production/Stable
Classifier: Intended Audience :: Developers
Classifier: Operating System :: Microsoft :: Windows
Classifier: Operating System :: POSIX
Classifier: Programming Language :: Python
Classifier: Programming Language :: Python :: 3 :: Only
Classifier: Programming Language :: Python :: 3
Classifier: Programming Language :: Python :: 3.6
Classifier: Programming Language :: Python :: 3.7
Classifier: Programming Language :: Python :: 3.8
Classifier: Programming Language :: Python :: 3.9
Classifier: Programming Language :: Python :: 3.10
Classifier: Programming Language :: Python :: 3.11
Classifier: Programming Language :: Python :: Implementation :: CPython
Requires-Python: >=3.6, <4
